ltl_graph_parser.py
ltl_parser_pkg-0.1.2.dist-info/LICENSE
ltl_parser_pkg-0.1.2.dist-info/METADATA
ltl_parser_pkg-0.1.2.dist-info/WHEEL
ltl_parser_pkg-0.1.2.dist-info/top_level.txt
ltl_parser_pkg-0.1.2.dist-info/RECORD
