Metadata-Version: 2.1
Name: ltl-parser-pkg
Version: 0.1.2
Summary: Parse the DOT file generated from SPOT API and creates a Graph with node-edge information.
Home-page: https://github.com/rezaurrakib/ltl_parser
Author: Md Rezaur Rahman
Author-email: rakib08cse@gmail.com
License: UNKNOWN
Platform: UNKNOWN
Classifier: Programming Language :: Python :: 3
Classifier: License :: OSI Approved :: MIT License
Classifier: Operating System :: OS Independent
